LICENSE
MANIFEST.in
README.md
package.json
setup.py
dash_masonry/DashMasonry.py
dash_masonry/__init__.py
dash_masonry/_imports_.py
dash_masonry/dash_masonry.min.js
dash_masonry/dash_masonry.min.js.map
dash_masonry/metadata.json
dash_masonry/package-info.json
dash_masonry.egg-info/PKG-INFO
dash_masonry.egg-info/SOURCES.txt
dash_masonry.egg-info/dependency_links.txt
dash_masonry.egg-info/top_level.txt