Metadata-Version: 2.1
Name: dash-masonry
Version: 0.0.2
Summary: React Masonry Component for Dash
Home-page: UNKNOWN
Author: Alex Towers <alexanderjtowers@gmail.com>
License: MIT
Platform: UNKNOWN
Classifier: Framework :: Dash
License-File: LICENSE
